wtfport/__init__.py
wtfport/cli.py
wtfport_cli-1.0.5.dist-info/licenses/LICENSE
wtfport_cli-1.0.5.dist-info/METADATA
wtfport_cli-1.0.5.dist-info/WHEEL
wtfport_cli-1.0.5.dist-info/entry_points.txt
wtfport_cli-1.0.5.dist-info/top_level.txt
wtfport_cli-1.0.5.dist-info/RECORD
