Metadata-Version: 2.4
Name: wtfport-cli
Version: 1.0.5
Summary: Find what’s using a TCP or UDP port
Author: Anil Raj Rimal
Author-email: Anil Raj Rimal <anilrajrimal@gmail.com>
License: MIT
Requires-Python: >=3.9
License-File: LICENSE
Requires-Dist: psutil
Dynamic: author
Dynamic: license-file
Dynamic: requires-python
